AUTHORS
ChangeLog
LICENSE
README
Vagrantfile
requirements.txt
setup.cfg
setup.py
config/serf-node1.json
config/serf-node2.json
config/serf-node3.json
examples/handle.py
examples/handlers/dns/member_join.py
examples/handlers/dns/member_leave.py
examples/handlers/node/member_join.sh
examples/handlers/node/query_deploy.py
serf_plugin_handler.egg-info/PKG-INFO
serf_plugin_handler.egg-info/SOURCES.txt
serf_plugin_handler.egg-info/dependency_links.txt
serf_plugin_handler.egg-info/not-zip-safe
serf_plugin_handler.egg-info/pbr.json
serf_plugin_handler.egg-info/top_level.txt
sph/__init__.py