Metadata-Version: 1.1
Name: serf-plugin-handler
Version: 0.2.0
Summary: Collins serf pluginable event handler
Home-page: https://github.com/aboutyou/serf-plugin-handler
Author: Collins GmbH & Co. KG
Author-email: info@project-collins.com
License: UNKNOWN
Platform: UNKNOWN
Classifier: Environment :: Console
Classifier: Intended Audience :: Developers
Classifier: License :: Other/Proprietary License
Classifier: Operating System :: POSIX :: Linux
Classifier: Operating System :: MacOS :: MacOS X
Classifier: Programming Language :: Python
Classifier: Programming Language :: Python :: 2
Classifier: Programming Language :: Python :: 2.7
Classifier: Programming Language :: Python :: 2.6
Classifier: Topic :: Software Development :: Libraries
